mcp_ikman_extractor/__init__.py
mcp_ikman_extractor/server.py
mcp_ikman_extractor-0.1.8.dist-info/licenses/LICENSE
mcp_ikman_extractor-0.1.8.dist-info/METADATA
mcp_ikman_extractor-0.1.8.dist-info/WHEEL
mcp_ikman_extractor-0.1.8.dist-info/entry_points.txt
mcp_ikman_extractor-0.1.8.dist-info/top_level.txt
mcp_ikman_extractor-0.1.8.dist-info/RECORD
